setup.py
hklab/__init__.py
hklab/cFunction.py
hklab.egg-info/PKG-INFO
hklab.egg-info/SOURCES.txt
hklab.egg-info/dependency_links.txt
hklab.egg-info/requires.txt
hklab.egg-info/top_level.txt