Metadata-Version: 1.0
Name: hklab
Version: 0.5.0
Summary: Fintech API
Home-page: https://github.com/hyokwan/
Author: kimhyokwan
Author-email: haiteam@naver.com
License: UNKNOWN
Keywords: calendar,list op
Platform: UNKNOWN
